langchain_qwq_modification/__init__.py
langchain_qwq_modification/chat_models.py
langchain_qwq_modification/py.typed
langchain_qwq_modification-0.1.0.dist-info/LICENSE
langchain_qwq_modification-0.1.0.dist-info/METADATA
langchain_qwq_modification-0.1.0.dist-info/WHEEL
langchain_qwq_modification-0.1.0.dist-info/RECORD
