Metadata-Version: 2.3
Name: langchain-qwq-modification
Version: 0.1.0
Summary: An integration package connecting QwQ and LangChain
License: MIT
Author: Yiğit Bekir Kaya, PhD
Author-email: yigit353@gmail.com
Requires-Python: >=3.9,<4.0
Classifier: License :: OSI Approved :: MIT License
Classifier: Programming Language :: Python :: 3
Classifier: Programming Language :: Python :: 3.9
Classifier: Programming Language :: Python :: 3.10
Classifier: Programming Language :: Python :: 3.11
Classifier: Programming Language :: Python :: 3.12
Classifier: Programming Language :: Python :: 3.13
Provides-Extra: codespell
Provides-Extra: docs
Provides-Extra: lint
Provides-Extra: test
Provides-Extra: typing
Requires-Dist: json-repair (>=0.40.0,<0.41.0)
Requires-Dist: langchain-core (>=0.3.15,<0.4.0)
Requires-Dist: langchain-openai (>=0.3.11,<0.4.0)
Requires-Dist: openai (>=1.70.0,<2.0.0)
Requires-Dist: python-dotenv (>=1.1.0,<2.0.0) ; extra == "test"
Project-URL: Repository, https://github.com/worship-dog/langchain-qwq
Project-URL: Release Notes, https://github.com/langchain-ai/langchain/releases?q=tag%3A%22qwq%3D%3D0%22&expanded=true
Project-URL: Source Code, https://github.com/worship-dog/langchain-qwq/tree/main/langchain_qwq
